

<Health>999</Health>
<MaxHealthValue>999</MaxHealthValue>

<critical_wound_threshold>5000.1</critical_wound_threshold>
<critical_wound_decrease_quant>1</critical_wound_decrease_quant>
<critical_wound_weights>1,1,1</critical_wound_weights>

<strike_immunity>0.0</strike_immunity>
<wound_immunity>0.0</wound_immunity>
<explosion_immunity>0.0</explosion_immunity>
<fire_wound_immunity>0.0</fire_wound_immunity>
<wound_2_immunity>0.0</wound_2_immunity>

<power_hit_part>0.0</power_hit_part>
<health_hit_part>0.0</health_hit_part>
<health_restore_v>0.1</health_restore_v>

<bleeding_v>0.0</bleeding_v>
<wound_incarnation_v>0.1</wound_incarnation_v>
<min_wound_size>0.000001</min_wound_size>

