<?xml version='1.0' encoding="windows-1251"?>

<game_information_portions>
  <info_portion id="storyline_actor_start">
    <task>storyline_eliminate_gunslinger</task>
  </info_portion>

  <info_portion id="global_dialogs">
    <dialog>actor_break_dialog</dialog>
<!--    <dialog>actor_help_wounded</dialog>   -->
  </info_portion>

  <info_portion id="OGSE_FINAL_2"/> 
  <info_portion id="OGSE_LIANA_PATCH_3_FIX"/> 
  <info_portion id="OGSE_KOLYA_PATCH_6_FIX"/> 
  <info_portion id="OGSE_PATCH_8_FIX"/> 
  <info_portion id="OGSE_KOLYA_PATCH_10_FIX"/>
  <info_portion id="OGSE_PATCH_10_1_FIX"/>

  <info_portion id="terrain_test">
  </info_portion>


  <!-- special info portion that sends to actor when it
    use in-game UI (PDA, Inventory, etc)-->
    
    <info_portion id="ui_pda">
		<disable>ui_pda_hide</disable>
    </info_portion>
    <info_portion id="ui_pda_hide">
		<disable>ui_pda</disable>
    </info_portion>
          
   <info_portion id="ui_pda_contacts"></info_portion>
   <info_portion id="ui_pda_contacts_hide"></info_portion>
   
   <info_portion id="ui_pda_map_local"></info_portion>
   <info_portion id="ui_pda_map_global"></info_portion>
   
   <info_portion id="ui_pda_news"></info_portion>
   <info_portion id="ui_pda_news_hide"></info_portion>
   
   <info_portion id="ui_pda_jobs_failed"></info_portion>
   <info_portion id="ui_pda_jobs_accomplished"></info_portion>
   <info_portion id="ui_pda_jobs_current"></info_portion>
   
    <info_portion id="ui_pda_jobs">
		<disable>ui_pda_jobs_hide</disable>
    </info_portion>
    <info_portion id="ui_pda_jobs_hide">
		<disable>ui_pda_jobs</disable>
    </info_portion>

   
   <info_portion id="ui_pda_contracts"></info_portion>
   
   <info_portion id="ui_pda_diary"></info_portion>
   <info_portion id="ui_pda_diary_hide"></info_portion>
      
   
   <info_portion id="ui_pda_encyclopedia"></info_portion>
   <info_portion id="ui_pda_encyclopedia_hide"></info_portion>
   
   <info_portion id="ui_pda_actor_info"></info_portion>
   <info_portion id="ui_pda_ranking"></info_portion>
   <info_portion id="ui_pda_events"></info_portion>
   
   <info_portion id="ui_inventory">
		<disable>ui_inventory_hide</disable>
   </info_portion>
   <info_portion id="ui_inventory_hide">
		<disable>ui_inventory</disable>
   </info_portion>

    <info_portion id="ui_talk">
		<disable>ui_talk_hide</disable>
    </info_portion>
    <info_portion id="ui_talk_hide">
		<disable>ui_talk</disable>
    </info_portion>
	<info_portion id="ogse_trade_hide">
	</info_portion>

    <info_portion id="ui_trade">
		<disable>ui_trade_hide</disable>
    </info_portion>
    <info_portion id="ui_trade_hide">
		<action>ogse_quests.unblock_use_hotkeys</action>	
		<disable>ui_trade</disable>
    </info_portion>

    <info_portion id="ui_car_body">
		<disable>ui_car_body_hide</disable>
    </info_portion>
    <info_portion id="ui_car_body_hide">
		<disable>ui_car_body</disable>
    </info_portion>


   <info_portion id="tutorial_part_15_hide_weapon"></info_portion>


	<info_portion id="autojump_enabled"></info_portion>
	
	
	<info_portion id="bioradar_dog"></info_portion>
	<info_portion id="bioradar_psevdodog"></info_portion>
	<info_portion id="bioradar_flesh"></info_portion>
	<info_portion id="bioradar_boar"></info_portion>
	<info_portion id="bioradar_tushkano"></info_portion>
	<info_portion id="bioradar_krovosos"></info_portion>
	<info_portion id="bioradar_burer"></info_portion>
	<info_portion id="bioradar_zombie"></info_portion>
	<info_portion id="bioradar_snork"></info_portion>
	<info_portion id="bioradar_kontroler"></info_portion>
	<info_portion id="bioradar_poltergeist"></info_portion>
	<info_portion id="bioradar_psevdogigant"></info_portion>
	<info_portion id="bioradar_cat"></info_portion>
	<info_portion id="bioradar_chimera"></info_portion>
	<info_portion id="bioradar_stalker"></info_portion>
	

	
	<info_portion id="rain_is_going_now"></info_portion>


	<info_portion id="btr_targeting_computer"></info_portion>




	<info_portion id="mayatnik_escape"></info_portion>
	<info_portion id="mayatnik_garb"></info_portion>
	<info_portion id="mayatnik_agro"></info_portion>
	<info_portion id="mayatnik_agr_under"></info_portion>
	<info_portion id="mayatnik_darkv"></info_portion>
	<info_portion id="mayatnik_x18"></info_portion>
	<info_portion id="mayatnik_bar"></info_portion>
	<info_portion id="mayatnik_rostok"></info_portion>
	<info_portion id="mayatnik_military"></info_portion>
	<info_portion id="mayatnik_yant"></info_portion>
	<info_portion id="mayatnik_x16"></info_portion>
	<info_portion id="mayatnik_radar"></info_portion>
	<info_portion id="mayatnik_x10"></info_portion>
	<info_portion id="mayatnik_prip"></info_portion>
	<info_portion id="mayatnik_chaes1"></info_portion>
	<info_portion id="mayatnik_chaes2"></info_portion>
	<info_portion id="mayatnik_sark"></info_portion>
	<info_portion id="mayatnik_city"></info_portion>
	<info_portion id="mayatnik_darksc"></info_portion>
	<info_portion id="mayatnik_marsh"></info_portion>

	<info_portion id="stalin_close_door"></info_portion>
	<info_portion id="stalin_forget"></info_portion>
	<info_portion id="stalin_first_talk"></info_portion>
	<info_portion id="stalin_propusk_forewer"></info_portion>
	<info_portion id="stalin_is_watching_you"></info_portion>	

	<info_portion id="caravan_loader_dead"><action>jekan_work.spawn_loader_cargo</action></info_portion>
	<info_portion id="caravan_guard1_dead"></info_portion>
	<info_portion id="caravan_guard2_dead"></info_portion>
	<info_portion id="caravan_hit_by_actor"><action>jekan_work.barman_offense_tip</action></info_portion>
	<info_portion id="karovan_go_back"></info_portion>



</game_information_portions>